theia_dumper/__init__.py
theia_dumper/cli.py
theia_dumper/diff.py
theia_dumper/logger.py
theia_dumper/py.typed
theia_dumper/raster.py
theia_dumper/stac.py
theia_dumper-0.2.8.dist-info/licenses/LICENSE
theia_dumper-0.2.8.dist-info/METADATA
theia_dumper-0.2.8.dist-info/WHEEL
theia_dumper-0.2.8.dist-info/entry_points.txt
theia_dumper-0.2.8.dist-info/top_level.txt
theia_dumper-0.2.8.dist-info/RECORD
