Metadata-Version: 2.4
Name: theia_dumper
Version: 0.2.8
Summary: THEIA-MTP geospatial data publisher
Author-email: Rémi Cresson <remi.cresson@inrae.fr>, Pablo Boizeau <pablo.boizeau@ird.fr>
License: Apache-2.0
Classifier: Programming Language :: Python :: 3.9
Classifier: Programming Language :: Python :: 3.10
Classifier: Programming Language :: Python :: 3.11
Classifier: Topic :: Scientific/Engineering :: GIS
Classifier: Topic :: Scientific/Engineering :: Image Processing
Classifier: License :: OSI Approved :: Apache Software License
Classifier: Operating System :: OS Independent
Requires-Python: >=3.9
License-File: LICENSE
Requires-Dist: setuptools
Requires-Dist: pystac
Requires-Dist: pystac_client
Requires-Dist: dinamis_sdk>=0.5.1
Requires-Dist: requests
Requires-Dist: click
Requires-Dist: rich
Requires-Dist: rasterio
Requires-Dist: rio-cogeo
Requires-Dist: rio_stac
Provides-Extra: test
Requires-Dist: pytest; extra == "test"
Requires-Dist: coverage; extra == "test"
Dynamic: license-file
